fastEASE/__init__.py
fastEASE/fastEASE.py
fastease-0.4.5.dist-info/LICENSE
fastease-0.4.5.dist-info/METADATA
fastease-0.4.5.dist-info/WHEEL
fastease-0.4.5.dist-info/top_level.txt
fastease-0.4.5.dist-info/RECORD
