Metadata-Version: 2.2
Name: fastEASE
Version: 0.4.5
Summary: An easy-to-use Python library for building EASE recommendation systems with CUDA
Author-email: Fedor Krasnov <krasnov.fedor2@wb.ru>
License: MIT License
Project-URL: Homepage, https://github.com/fkrasnov2/fastEASE
Project-URL: Repository, https://github.com/fkrasnov2/fastEASE
Keywords: recsys,recommendation systems,machine learning,AI,personalization
Classifier: Development Status :: 3 - Alpha
Classifier: Topic :: Scientific/Engineering :: Artificial Intelligence
Classifier: Programming Language :: Python :: 3.10
Classifier: Programming Language :: Python :: 3.11
Classifier: Programming Language :: Python :: 3.12
Classifier: Programming Language :: Python :: 3
Classifier: Topic :: Software Development :: Libraries :: Python Modules
Classifier: Intended Audience :: Science/Research
Classifier: Intended Audience :: Education
Classifier: Operating System :: Unix
Classifier: Operating System :: MacOS
Classifier: Operating System :: Microsoft :: Windows
Requires-Python: >=3.10
License-File: LICENSE
Requires-Dist: numpy==2.2.2
Requires-Dist: scikit-learn==1.6.1
Requires-Dist: scipy==1.15.1
Requires-Dist: tqdm==4.67.1
